{
  "amis":
  {
    "region_0": "ami-774fce08"
  },
  "protocol":"Semi-Honest-BMR",
  "numOfParties":
  {
    "size_0":3
  },
  "gitAddress": "https://github.com/cryptobiu/Semi-Honest-BMR.git",
  "aWSInstType": "c4.large",
  "aWWSBidPrice": "0.07",
  "executableName": "SemiHonestBMR",
  "configurations":
  {
    "conf_0": "-circuitFile@3Party/AESout@-inputsFile@3Party/aesP0@-partiesFile@parties.conf@-key@3Party/aesP@-version@2",
    "conf_1": "-circuitFile@3Party/AESout@-inputsFile@3Party/aesP0@-partiesFile@parties.conf@-key@3Party/aesP@-version@3",
    "conf_2": "-circuitFile@3Party/AESout@-inputsFile@3Party/aesP0@-partiesFile@parties.conf@-key@3Party/aesP@-version@4"
  },
  "numOfRepetitions":1,
  "numOfInternalRepetitions":1,
  "isSpotRequest": "True",
  "gitBranch": "experimentation",
  "IsPublished": "True",
  "isExternal": "False",
  "regions":
  {
    "region_0":"us-east-1b"
  },
  "workingDirectory": "~/Semi-Honest-BMR",
  "resultsDirectory": "~/MATRIX/ExperimentReport/Results",
  "emails":
  {
    "email_0":"liork.cryptobiu@gmail.com"
  },
  "institute":"Bar Ilan Cyber Center"
}

